{"_type":"export","__export_format":4,"__export_date":"2021-08-27T23:54:35.044Z","__export_source":"insomnia.desktop.app:v2021.4.1","resources":[{"_id":"req_2aaaa9ae21124f95893443268a726925","parentId":"fld_0e9045b68c434d60a0e978815ea2fe01","modified":1629941258967,"created":1629915884221,"url":"http://localhost:3000/conta/extrato","name":"Extrato","description":"","method":"GET","body":{},"parameters":[{"id":"pair_71523891e3d04696b05c43de595808be","name":"numero_conta","value":"1629941113851","description":""},{"id":"pair_abcdf68734db4a0aa714a8abb9aacbf3","name":"senha","value":"12345","description":""}],"headers":[],"authentication":{},"metaSortKey":-1629915884221,"isPrivate":false,"settingStoreCookies":true,"settingSendCookies":true,"settingDisableRenderRequestBody":false,"settingEncodeUrl":true,"settingRebuildPath":true,"settingFollowRedirects":"global","_type":"request"},{"_id":"fld_0e9045b68c434d60a0e978815ea2fe01","parentId":"wrk_40a8810f3bd940f7816fae7fe086ebb4","modified":1629915876471,"created":1629915876471,"name":"Conta","description":"","environment":{},"environmentPropertyOrder":null,"metaSortKey":-1629915876471,"_type":"request_group"},{"_id":"wrk_40a8810f3bd940f7816fae7fe086ebb4","parentId":null,"modified":1629741669368,"created":1629741669368,"name":"Desafio 2 - Backend API Banco Digital","description":"","scope":"collection","_type":"workspace"},{"_id":"req_1f32ab66f6e74bc380f81dffd4d946b1","parentId":"fld_eb72ba8307fe4d74b8cd15c2b4ce9b03","modified":1629940412036,"created":1629901362838,"url":"http://localhost:3000/transacoes/depositar","name":"Depositar","description":"","method":"POST","body":{"mimeType":"application/json","text":"{\n    \"numero_conta\": \"1629940404872\",\n    \"valor\": 1020\n}"},"parameters":[{"id":"pair_aa1a85a374144559a5d5a4da8539bada","name":"senha_banco","value":"Cubos123Bank","description":""}],"headers":[{"name":"Content-Type","value":"application/json","id":"pair_638df4456bdb4bef8b5f93900a3af93f"}],"authentication":{},"metaSortKey":-1629901362838,"isPrivate":false,"settingStoreCookies":true,"settingSendCookies":true,"settingDisableRenderRequestBody":false,"settingEncodeUrl":true,"settingRebuildPath":true,"settingFollowRedirects":"global","_type":"request"},{"_id":"fld_eb72ba8307fe4d74b8cd15c2b4ce9b03","parentId":"wrk_40a8810f3bd940f7816fae7fe086ebb4","modified":1629901331870,"created":1629901331870,"name":"Transações","description":"","environment":{},"environmentPropertyOrder":null,"metaSortKey":-1629901331870,"_type":"request_group"},{"_id":"req_2f5cd52686a3432b84e5010f475d2f2e","parentId":"fld_eb72ba8307fe4d74b8cd15c2b4ce9b03","modified":1629941235118,"created":1629902285032,"url":"http://localhost:3000/transacoes/sacar","name":"Sacar","description":"","method":"POST","body":{"mimeType":"application/json","text":"{\n    \"numero_conta\": \"1629941125561\",\n    \"valor\": 200,\n\t\t\"senha\": \"12345\"\n}"},"parameters":[{"id":"pair_4b22ea5f7e024a02b51d750cea371e84","name":"senha_banco","value":"Cubos123Bank","description":""}],"headers":[{"name":"Content-Type","value":"application/json","id":"pair_a15e6f0d96024b7bbee14f85291d3fd2"}],"authentication":{},"metaSortKey":-1629901362788,"isPrivate":false,"settingStoreCookies":true,"settingSendCookies":true,"settingDisableRenderRequestBody":false,"settingEncodeUrl":true,"settingRebuildPath":true,"settingFollowRedirects":"global","_type":"request"},{"_id":"req_4f42415206164afc87ecc7371a026f10","parentId":"fld_eb72ba8307fe4d74b8cd15c2b4ce9b03","modified":1629941225980,"created":1629903233314,"url":"http://localhost:3000/transacoes/transferir","name":"Transferir","description":"","method":"POST","body":{"mimeType":"application/json","text":"{\n    \"numero_conta_origem\": \"1629941113851\",\n    \"numero_conta_destino\": \"1629941125561\",\n    \"valor\": 900,\n\t  \"senha\": \"12345\"\n}"},"parameters":[{"id":"pair_0752e5e394a34db782f7930de8cb68ea","name":"senha_banco","value":"Cubos123Bank","description":""}],"headers":[{"name":"Content-Type","value":"application/json","id":"pair_23aa74c1d52d4fe59121b30d7f020cd4"}],"authentication":{},"metaSortKey":-1629901362738,"isPrivate":false,"settingStoreCookies":true,"settingSendCookies":true,"settingDisableRenderRequestBody":false,"settingEncodeUrl":true,"settingRebuildPath":true,"settingFollowRedirects":"global","_type":"request"},{"_id":"req_0473c59f996d41fbb6f8503ceb695a8d","parentId":"fld_eb72ba8307fe4d74b8cd15c2b4ce9b03","modified":1629941204822,"created":1629904780091,"url":"http://localhost:3000/transacoes/saldo","name":"Saldo","description":"","method":"GET","body":{},"parameters":[{"id":"pair_3b278a561b4a4bcd935173468463a701","name":"numero_conta","value":"1629941113851","description":""},{"id":"pair_07a15bd613c3410e8a96fa0c03d65b8d","name":"senha","value":"12345","description":""}],"headers":[],"authentication":{},"metaSortKey":-1629901362688,"isPrivate":false,"settingStoreCookies":true,"settingSendCookies":true,"settingDisableRenderRequestBody":false,"settingEncodeUrl":true,"settingRebuildPath":true,"settingFollowRedirects":"global","_type":"request"},{"_id":"req_80d2740f01b843d7976f17d7beed0a4f","parentId":"fld_49872acc046e4efd850f5b3a54d2edc1","modified":1630104384385,"created":1629742835174,"url":"http://localhost:3000/contas","name":"Obter contas","description":"","method":"GET","body":{},"parameters":[{"id":"pair_26c6c7f1ffdb4aa8adbb264e8495ebc4","name":"senha_banco","value":"Cubos123Bank","description":""}],"headers":[],"authentication":{},"metaSortKey":-1629741680699,"isPrivate":false,"settingStoreCookies":true,"settingSendCookies":true,"settingDisableRenderRequestBody":false,"settingEncodeUrl":true,"settingRebuildPath":true,"settingFollowRedirects":"global","_type":"request"},{"_id":"fld_49872acc046e4efd850f5b3a54d2edc1","parentId":"wrk_40a8810f3bd940f7816fae7fe086ebb4","modified":1629742824203,"created":1629742824203,"name":"Contas","description":"","environment":{},"environmentPropertyOrder":null,"metaSortKey":-1629742824203,"_type":"request_group"},{"_id":"req_b65dc35c69c34dc49fcd3e10dfca2b09","parentId":"fld_49872acc046e4efd850f5b3a54d2edc1","modified":1630108263352,"created":1629742942770,"url":"http://localhost:3000/contas","name":"Criar conta","description":"","method":"POST","body":{"mimeType":"application/json","text":"{\n\t\"nome\": \"Foo Bar 2\",\n\t\"cpf\": \"00011sa12233\",\n\t\"data_nascimento\": \"2021-03-15\",\n\t\"telefone\": \"71999998888\",\n\t\"email\": \"teste@taffarel.com\",\n\t\"senha\": \"12345\"\n}"},"parameters":[{"id":"pair_db7f7363db084275915464e1b7997a0b","name":"senha_banco","value":"Cubos123Bank","description":""}],"headers":[{"name":"Content-Type","value":"application/json","id":"pair_1a537e28736d48eda8498c1e702ce910"}],"authentication":{},"metaSortKey":-1629741680649,"isPrivate":false,"settingStoreCookies":true,"settingSendCookies":true,"settingDisableRenderRequestBody":false,"settingEncodeUrl":true,"settingRebuildPath":true,"settingFollowRedirects":"global","_type":"request"},{"_id":"req_bf3728a36d9f4ed6a4ebe1076851efed","parentId":"fld_49872acc046e4efd850f5b3a54d2edc1","modified":1630105516851,"created":1629759060361,"url":"http://localhost:3000/contas/1630102409153/usuario","name":"Atualizar conta","description":"","method":"PATCH","body":{"mimeType":"application/json","text":"{\n\t\"nome\": \"Pedro\",\n\t\"email\": \"taffarel555@bol.com\"\n}"},"parameters":[{"id":"pair_23223adc5c264db3932bc14c72031eba","name":"senha_banco","value":"Cubos123Bank","description":""}],"headers":[{"name":"Content-Type","value":"application/json","id":"pair_7de8a2143ad04cf2a7ecb45e6e604325"}],"authentication":{},"metaSortKey":-1629741680624,"isPrivate":false,"settingStoreCookies":true,"settingSendCookies":true,"settingDisableRenderRequestBody":false,"settingEncodeUrl":true,"settingRebuildPath":true,"settingFollowRedirects":"global","_type":"request"},{"_id":"req_a50e57a4e1c7407987d97e64b2f34895","parentId":"fld_49872acc046e4efd850f5b3a54d2edc1","modified":1629941158798,"created":1629762066917,"url":"http://localhost:3000/contas/1629941113851/usuario","name":"Substituir conta","description":"","method":"PUT","body":{"mimeType":"application/json","text":"{\n  \"numero\": \"1629941113851\",\n  \"saldo\": 10000,\n  \"usuario\": {\n    \"nome\": \"asdasd\",\n    \"cpf\": \"00011122233\",\n    \"data_nascimento\": \"2021-07-15\",\n    \"telefone\": \"71999998888\",\n    \"email\": \"asd@taffarel.com\",\n    \"senha\": \"12345\"\n  }\n}"},"parameters":[{"id":"pair_d4862d98f5ca457cbd9f6984b4d0ed07","name":"senha_banco","value":"Cubos123Bank","description":""}],"headers":[{"name":"Content-Type","value":"application/json","id":"pair_1dfdf17c578e4cdd96b558c2581e70d0"}],"authentication":{},"metaSortKey":-1629741680549,"isPrivate":false,"settingStoreCookies":true,"settingSendCookies":true,"settingDisableRenderRequestBody":false,"settingEncodeUrl":true,"settingRebuildPath":true,"settingFollowRedirects":"global","_type":"request"},{"_id":"req_b352bebee6c546c3968e8be440797a74","parentId":"fld_49872acc046e4efd850f5b3a54d2edc1","modified":1629941180936,"created":1629768557616,"url":"http://localhost:3000/contas/1629941174671","name":"Deletar conta","description":"","method":"DELETE","body":{},"parameters":[{"id":"pair_f7be8192f6634f679079176b2e26fc82","name":"senha_banco","value":"Cubos123Bank","description":""}],"headers":[],"authentication":{},"metaSortKey":-1629741680499,"isPrivate":false,"settingStoreCookies":true,"settingSendCookies":true,"settingDisableRenderRequestBody":false,"settingEncodeUrl":true,"settingRebuildPath":true,"settingFollowRedirects":"global","_type":"request"},{"_id":"env_a4622bedadcb8a05058c69fe8acb7818843e9ad9","parentId":"wrk_40a8810f3bd940f7816fae7fe086ebb4","modified":1629741669443,"created":1629741669443,"name":"Base Environment","data":{},"dataPropertyOrder":null,"color":null,"isPrivate":false,"metaSortKey":1629741669443,"_type":"environment"},{"_id":"jar_a4622bedadcb8a05058c69fe8acb7818843e9ad9","parentId":"wrk_40a8810f3bd940f7816fae7fe086ebb4","modified":1629741669444,"created":1629741669444,"name":"Default Jar","cookies":[],"_type":"cookie_jar"},{"_id":"spc_8d91d72b915a4a738fad4882070c6e9a","parentId":"wrk_40a8810f3bd940f7816fae7fe086ebb4","modified":1629741669376,"created":1629741669376,"fileName":"Desafio 2 - Backend API Banco Digital","contents":"","contentType":"yaml","_type":"api_spec"}]}